[
    {
      "id": 2,
      "observation_type_id": 4,
      "social_program_id": 1
    },
    {
      "id": 3,
      "observation_type_id": 3,
      "social_program_id": 1
    },
    {
      "id": 4,
      "observation_type_id": 2,
      "social_program_id": 1
    },
    {
      "id": 5,
      "observation_type_id": 1,
      "social_program_id": 1
    },
    {
      "id": 6,
      "observation_type_id": 4,
      "social_program_id": 1
    },
    {
      "id": 10,
      "observation_type_id": 1,
      "social_program_id": 1
    },
    {
      "id": 11,
      "observation_type_id": 1,
      "social_program_id": 1
    },
    {
      "id": 12,
      "observation_type_id": 3,
      "social_program_id": 1
    }
  ]